flake8_ugettext_alias.py
flake8_ugettext_alias-1.1.dist-info/DESCRIPTION.rst
flake8_ugettext_alias-1.1.dist-info/METADATA
flake8_ugettext_alias-1.1.dist-info/RECORD
flake8_ugettext_alias-1.1.dist-info/WHEEL
flake8_ugettext_alias-1.1.dist-info/entry_points.txt
flake8_ugettext_alias-1.1.dist-info/metadata.json
flake8_ugettext_alias-1.1.dist-info/top_level.txt
