Metadata-Version: 2.0
Name: flake8-ugettext-alias
Version: 1.1
Summary: ugettext alias checker plugin for flake8
Home-page: https://github.com/unleashed/flake8-ugettext-alias
Author: Unleashed NV
Author-email: development@unleashed.be
License: MIT
Keywords: flake8 ugettext alias
Platform: UNKNOWN
Classifier: Development Status :: 3 - Alpha
Classifier: Environment :: Console
Classifier: Intended Audience :: Developers
Classifier: License :: OSI Approved :: MIT License
Classifier: Operating System :: OS Independent
Classifier: Programming Language :: Python
Classifier: Programming Language :: Python :: 2
Classifier: Programming Language :: Python :: 3
Classifier: Topic :: Software Development :: Libraries :: Python Modules
Classifier: Topic :: Software Development :: Quality Assurance
Requires-Dist: flake8
